{
  "sections": {
    "f70a0cc6-0eca-46fd-91b2-cd193c00ac1c": {
      "type": "main-section-header",
      "settings": {
        "section_heading": "焼きたてのコーヒー豆",
        "heading_size": "xl",
        "section_sub_heading": "COFFEE BEANS",
        "change_box_layout": false,
        "description": "",
        "show_description": false,
        "image": "shopify:\/\/shop_images\/image2771.jpg"
      }
    },
    "8ea36c2b-cf70-4588-8cab-8479b9def8dd": {
      "type": "collection-beens-section",
      "blocks": {
        "1f70d9b9-b476-4ad6-8431-7b67f7e47934": {
          "type": "column",
          "settings": {
            "link_label": "ブレンド豆",
            "link": "#blend"
          }
        },
        "4cf82d1c-6955-492b-a7f2-14f9b32792a4": {
          "type": "column",
          "settings": {
            "link_label": "アフリカのコーヒー豆",
            "link": "#african"
          }
        },
        "6d91e6e3-aa8b-4c6c-990c-e972bf788172": {
          "type": "column",
          "settings": {
            "link_label": "中米のコーヒー豆",
            "link": "#central_american"
          }
        },
        "0ca8a33e-6c8e-4c64-aab7-b25ee22037de": {
          "type": "column",
          "settings": {
            "link_label": "南米のコーヒー豆",
            "link": "#south_american"
          }
        },
        "0e52a22e-a7bb-433e-8655-8d46fe5a64b6": {
          "type": "column",
          "settings": {
            "link_label": "ディカフェ",
            "link": "#decaf"
          }
        }
      },
      "block_order": [
        "1f70d9b9-b476-4ad6-8431-7b67f7e47934",
        "4cf82d1c-6955-492b-a7f2-14f9b32792a4",
        "6d91e6e3-aa8b-4c6c-990c-e972bf788172",
        "0ca8a33e-6c8e-4c64-aab7-b25ee22037de",
        "0e52a22e-a7bb-433e-8655-8d46fe5a64b6"
      ],
      "settings": {
        "change_block": false,
        "section_heading": "<p>焼きたてコーヒー豆の新鮮さと<br\/>香りをお楽しみください<\/p>",
        "heading_size": "xl",
        "heading_text_align": "left",
        "description": "<p>A day in the coffeeでは注文をいただいてから焙煎を行う<strong>注文焙煎<\/strong>を行なって、皆様にお届けしております。<br\/>香り高いコーヒー豆の味わいをぜひお楽しみください。<br\/><br\/>また、コーヒーの定期便もご用意しております。<br\/>定期便に興味のある方は以下の「【コーヒー定期便】を詳しく見る」よりご確認ください。<\/p>",
        "description_text_align": "left"
      }
    },
    "b466eac5-a569-47e9-9d52-c4968c8089ef": {
      "type": "collection-subscription-section",
      "settings": {
        "change_block": true,
        "image": "shopify:\/\/shop_images\/image2575.jpg",
        "section_heading": "<p>コーヒー焙煎屋さんがお届けする、<br\/>焼きたてコーヒー豆の定期便<\/p>",
        "heading_size": "xl",
        "section_sub_heading": "SUBSCRIPTION",
        "description": "<p>コーヒー豆はやっぱり焼きたてが一番。コーヒーを飲むペースに合わせて、焼きたてのコーヒー豆を定期便でお届けします。<\/p>",
        "button-label": "【コーヒー定期便】を詳しく見る",
        "button-link": "\/pages\/subscription"
      }
    },
    "main": {
      "type": "main-list-collections",
      "disabled": true,
      "settings": {
        "title": "Collections",
        "sort": "alphabetical",
        "image_ratio": "square",
        "columns_desktop": 3,
        "columns_mobile": "2"
      }
    },
    "e840dd1c-bb6f-4e69-99fd-3653ff1de1e7": {
      "type": "featured-collection-been",
      "settings": {
        "image": "shopify:\/\/shop_images\/image_0823.jpg",
        "section_id": "blend",
        "heading_size": "xl",
        "change_box_layout": false,
        "description": "<p>コーヒーでそのお店の個性を出す。その方法としてA day in the coffee ではブレンドコーヒーをとても大事にしてます。産地や焙煎度合いをミックスして、コーヒーの魅力をより引き出すことができます。当店では、焙煎度合いで3種類「ライトブレンド」「ミディアムブレンド」「ストロングブレンド」と、季節ごとの「シーズンブレンド」の4種類ブレンドをご用意しています。ブレンドはコーヒーショップの顔のような存在。A day in the coffeeのブレンドをぜひ一度ご賞味ください。<\/p>",
        "show_description": false,
        "description_style": "body",
        "collection": "blend",
        "products_to_show": 25,
        "columns_desktop": 3,
        "full_width": false,
        "show_view_all": false,
        "view_all_style": "solid",
        "enable_desktop_slider": false,
        "color_scheme": "",
        "image_ratio": "adapt",
        "image_shape": "default",
        "show_secondary_image": false,
        "show_vendor": false,
        "show_rating": false,
        "enable_quick_add": false,
        "columns_mobile": "2",
        "swipe_on_mobile": false,
        "box_gap": "l"
      }
    },
    "1f8ec698-b23a-4ed8-8fd3-4eab6be698d2": {
      "type": "featured-collection-been",
      "settings": {
        "image": "shopify:\/\/shop_images\/image_africa2.jpg",
        "section_id": "african",
        "heading_size": "xl",
        "change_box_layout": true,
        "description": "<p>コーヒーの起源となっている地域。アフリカの大地を思わせるようなスパイス感のある豆が多く、特にエチオピアのコーヒーは風味が独特です。一方、ケニアはコク、風味ともに十分で昔から人気の高いコーヒー豆です。<\/p>",
        "show_description": false,
        "description_style": "body",
        "collection": "african",
        "products_to_show": 25,
        "columns_desktop": 3,
        "full_width": false,
        "show_view_all": true,
        "view_all_style": "solid",
        "enable_desktop_slider": false,
        "color_scheme": "",
        "image_ratio": "adapt",
        "image_shape": "default",
        "show_secondary_image": false,
        "show_vendor": false,
        "show_rating": false,
        "enable_quick_add": false,
        "columns_mobile": "2",
        "swipe_on_mobile": false,
        "box_gap": "l"
      }
    },
    "8c5d6e0d-3f26-461a-bbf3-05c407fe8d5e": {
      "type": "featured-collection-been",
      "settings": {
        "image": "shopify:\/\/shop_images\/image_middle2.jpg",
        "section_id": "central_american",
        "heading_size": "xl",
        "change_box_layout": false,
        "description": "<p>山岳地域でコーヒー豆が栽培されることが多く、標高差による寒暖差幅の大きさから、固くしまった品質の高いコーヒー豆の多いエリアです。すっきりとして甘みも十分、コーヒーのいいとこ取りをしたような印象のグアテマラのコーヒー豆は、当店でも人気が高いです。<\/p>",
        "show_description": false,
        "description_style": "body",
        "collection": "central_american",
        "products_to_show": 25,
        "columns_desktop": 3,
        "full_width": false,
        "show_view_all": false,
        "view_all_style": "solid",
        "enable_desktop_slider": false,
        "color_scheme": "",
        "image_ratio": "adapt",
        "image_shape": "default",
        "show_secondary_image": false,
        "show_vendor": false,
        "show_rating": false,
        "enable_quick_add": false,
        "columns_mobile": "2",
        "swipe_on_mobile": false,
        "box_gap": "l"
      }
    },
    "41117e49-4a0c-42df-b24b-11091e3e0718": {
      "type": "featured-collection-been",
      "settings": {
        "image": "shopify:\/\/shop_images\/image_south2.jpg",
        "section_id": "south_american",
        "heading_size": "xl",
        "change_box_layout": true,
        "description": "<p>プランテーションに代表されるような大規模農園で栽培されることが多く、生産量が多いことから味わいの印象が平均的なコーヒー豆の多い地域です。ブラジルのコーヒー豆のようにブレンド豆のベースに使われることが多いですが、一部ではコロンビア原種（ティピカ）のコーヒー豆や、南米西側エリアの山岳地域国のボリビアなどで栽培しているスペシャルティコーヒー豆などでは、コクも深く希少価値の高い豆も生産されています。<\/p>",
        "show_description": false,
        "description_style": "body",
        "collection": "south_american",
        "products_to_show": 25,
        "columns_desktop": 3,
        "full_width": false,
        "show_view_all": false,
        "view_all_style": "solid",
        "enable_desktop_slider": false,
        "color_scheme": "",
        "image_ratio": "adapt",
        "image_shape": "default",
        "show_secondary_image": false,
        "show_vendor": false,
        "show_rating": false,
        "enable_quick_add": false,
        "columns_mobile": "2",
        "swipe_on_mobile": false,
        "box_gap": "l"
      }
    },
    "89f0ec6a-2654-487a-84f5-699fd23386fd": {
      "type": "featured-collection-been",
      "settings": {
        "image": "shopify:\/\/shop_images\/image_2759.jpg",
        "section_id": "decaf",
        "heading_size": "xl",
        "change_box_layout": false,
        "description": "<p>A day in the coffeeではディカフェの豆もご用意しております。子育て中でカフェインを制限したい方や、寝る前のひと時にコーヒーを楽しみたい方向けに、ディカフェのコーヒー豆を焼きたてでお届けしております。<\/p>",
        "show_description": false,
        "description_style": "body",
        "collection": "decaf",
        "products_to_show": 25,
        "columns_desktop": 3,
        "full_width": false,
        "show_view_all": true,
        "view_all_style": "solid",
        "enable_desktop_slider": false,
        "color_scheme": "",
        "image_ratio": "adapt",
        "image_shape": "default",
        "show_secondary_image": false,
        "show_vendor": false,
        "show_rating": false,
        "enable_quick_add": false,
        "columns_mobile": "2",
        "swipe_on_mobile": false,
        "box_gap": "default"
      }
    },
    "793bf923-d917-4523-ab4b-ee2c46577020": {
      "type": "fuatured-collection-other",
      "settings": {
        "collection": "arrange",
        "products_to_show": 25,
        "columns_desktop": 3,
        "columns_mobile": "2",
        "change_block": false,
        "image": "shopify:\/\/shop_images\/drip_howto00.jpg",
        "section_heading": "",
        "heading_size": "xl",
        "heading_text_align": "left",
        "description": "<p>まずはお気軽にコーヒーを楽しむ手段として、ドリップバッグやアイスコーヒーバッグなどの商品もご用意しております。<br\/>こちらの商品は店舗で1つずつパックして生産しており、なるべく焙煎鮮度の高いコーヒー豆をお届けできるよう努めています。<br\/>コーヒーの道具がない方も、お気軽にお楽しみいただけます。ひと味違う香り高いアレンジコーヒーも是非ご賞味ください。<\/p>",
        "description_text_align": "left"
      }
    }
  },
  "order": [
    "f70a0cc6-0eca-46fd-91b2-cd193c00ac1c",
    "8ea36c2b-cf70-4588-8cab-8479b9def8dd",
    "b466eac5-a569-47e9-9d52-c4968c8089ef",
    "main",
    "e840dd1c-bb6f-4e69-99fd-3653ff1de1e7",
    "1f8ec698-b23a-4ed8-8fd3-4eab6be698d2",
    "8c5d6e0d-3f26-461a-bbf3-05c407fe8d5e",
    "41117e49-4a0c-42df-b24b-11091e3e0718",
    "89f0ec6a-2654-487a-84f5-699fd23386fd",
    "793bf923-d917-4523-ab4b-ee2c46577020"
  ]
}
